Metadata-Version: 1.0
Name: gameserver-response-parser
Version: 0.3
Summary: a library to parse the responses of gameservers
Home-page: https://github.com/991jo/gameserver_response_parser
Author: 992jo
Author-email: UNKNOWN
License: WTF
Platform: UNKNOWN
